Tmsa7/__init__.py
Tmsa7/core/__init__.py
Tmsa7/core/doc.py
Tmsa7/core/example.py
Tmsa7/core/helper.py
Tmsa7-0.1.1.dist-info/METADATA
Tmsa7-0.1.1.dist-info/WHEEL
Tmsa7-0.1.1.dist-info/top_level.txt
Tmsa7-0.1.1.dist-info/RECORD
