Metadata-Version: 2.1
Name: Tmsa7
Version: 0.1.1
Requires-Dist: numpy
